__init__.py
notation_calc.py
easy_math_ms-0.1.0.dist-info/licenses/LICENCE
easy_math_ms-0.1.0.dist-info/METADATA
easy_math_ms-0.1.0.dist-info/WHEEL
easy_math_ms-0.1.0.dist-info/top_level.txt
easy_math_ms-0.1.0.dist-info/RECORD
