Metadata-Version: 2.4
Name: easy_math_ms
Version: 0.1.0
Summary: A packages for a mathmatical nations in a data-structure
Author-email: Mohammad Sadeghi <mohammadsadeghi1082@gmail.com>
Classifier: License :: OSI Approved :: MIT License
Classifier: Programming Language :: Python :: 3
Classifier: Operating System :: OS Independent
Requires-Python: >=3.7
License-File: LICENCE
Dynamic: license-file
